ansys/health/heart/__init__.py
ansys/health/heart/examples.py
ansys/health/heart/exceptions.py
ansys/health/heart/landmarks.py
ansys/health/heart/logger.py
ansys/health/heart/models.py
ansys/health/heart/models_utils.py
ansys/health/heart/objects.py
ansys/health/heart/parts.py
ansys/health/heart/simulator.py
ansys/health/heart/data_examples/left_purkinje.vtp
ansys/health/heart/data_examples/right_purkinje.vtp
ansys/health/heart/data_examples/rodero_01_fullheart_1.5mm.namemap.json
ansys/health/heart/data_examples/rodero_01_fullheart_1.5mm.partinfo.json
ansys/health/heart/data_examples/rodero_01_fullheart_1.5mm.vtu
ansys/health/heart/data_examples/rodero_01_fullheart_2.0mm.namemap.json
ansys/health/heart/data_examples/rodero_01_fullheart_2.0mm.partinfo.json
ansys/health/heart/data_examples/rodero_01_fullheart_2.0mm.vtu
ansys/health/heart/data_examples/rodero_01_leftventricle_part_definition.json
ansys/health/heart/data_examples/rodero_01_leftventricle_surface.vtp
ansys/health/heart/post/__init__.py
ansys/health/heart/post/auto_process.py
ansys/health/heart/post/dpf_utils.py
ansys/health/heart/post/klotz_curve.py
ansys/health/heart/post/laplace_post.py
ansys/health/heart/post/pvloop.py
ansys/health/heart/post/strain_calculator.py
ansys/health/heart/post/system_model_post.py
ansys/health/heart/pre/__init__.py
ansys/health/heart/pre/conduction_path.py
ansys/health/heart/pre/database_utils.py
ansys/health/heart/pre/input.py
ansys/health/heart/pre/mesher.py
ansys/health/heart/settings/__init__.py
ansys/health/heart/settings/settings.py
ansys/health/heart/settings/defaults/electrophysiology.py
ansys/health/heart/settings/defaults/fibers.py
ansys/health/heart/settings/defaults/mechanics.py
ansys/health/heart/settings/defaults/purkinje.py
ansys/health/heart/settings/defaults/zeropressure.py
ansys/health/heart/settings/material/cell_models.py
ansys/health/heart/settings/material/curve.py
ansys/health/heart/settings/material/ep_material.py
ansys_health_heart-0.15.0.dist-info/licenses/LICENSE
ansys_health_heart-0.15.0.dist-info/WHEEL
ansys_health_heart-0.15.0.dist-info/METADATA
ansys_health_heart-0.15.0.dist-info/RECORD
