Metadata-Version: 2.4
Name: ansys-health-heart
Version: 0.15.0
Summary: Python framework for heart modeling using ANSYS tools.
Author-email: "ANSYS, Inc." <pyansys.core@ansys.com>
Maintainer-email: "ANSYS, Inc." <pyansys.core@ansys.com>
Requires-Python: >=3.10,<4
Classifier: Development Status :: 4 - Beta
Classifier: Intended Audience :: Science/Research
Classifier: Topic :: Scientific/Engineering :: Information Analysis
Classifier: License :: OSI Approved :: MIT License
Classifier: Operating System :: OS Independent
Classifier: Programming Language :: Python :: 3.11
Classifier: Programming Language :: Python :: 3.12
License-File: LICENSE
Requires-Dist: ansys-dpf-core>=0.13.6,!=0.14.0,<0.15
Requires-Dist: ansys-fluent-core>=0.34.2
Requires-Dist: ansys.dyna.core>=0.7.1
Requires-Dist: deprecated>=1.2.18
Requires-Dist: h5py>=3.6.0
Requires-Dist: httpx>=0.27.2
Requires-Dist: matplotlib>=3.10.1
Requires-Dist: natsort>=8.4.0
Requires-Dist: networkx>=3.2.1
Requires-Dist: numpy<=2.2.6
Requires-Dist: pandas<=3.0.0
Requires-Dist: pint>=0.24.4
Requires-Dist: pyvista>=0.44.1,<0.46
Requires-Dist: rich>=13.9.4
Requires-Dist: scipy<=1.15.3
Requires-Dist: validators>=0.34.0
Requires-Dist: vtk>=9.1.0,<9.6,!=9.4.*
Requires-Dist: pydantic>=2.0.0
Requires-Dist: ansys-sphinx-theme[autoapi]==1.5.2 ; extra == "doc"
Requires-Dist: jupyter_sphinx==0.5.3 ; extra == "doc"
Requires-Dist: myst-parser==4.0.1 ; extra == "doc"
Requires-Dist: nbsphinx==0.9.7 ; extra == "doc"
Requires-Dist: numpydoc==1.8.0 ; extra == "doc"
Requires-Dist: pyvista[jupyter]==0.45.3 ; extra == "doc"
Requires-Dist: pypandoc==1.15 ; extra == "doc"
Requires-Dist: sphinx==8.1.3 ; extra == "doc"
Requires-Dist: sphinx-autodoc-typehints==3.0.1 ; extra == "doc"
Requires-Dist: sphinx-copybutton==0.5.2 ; extra == "doc"
Requires-Dist: sphinx-gallery==0.19.0 ; extra == "doc"
Requires-Dist: sphinx-jinja==2.0.2 ; extra == "doc"
Requires-Dist: sphinx_design ; extra == "doc"
Requires-Dist: sphinxcontrib-video==0.4.1 ; extra == "doc"
Requires-Dist: trame-vtk==2.10.0 ; extra == "doc"
Requires-Dist: pytest==8.4.2 ; extra == "tests"
Requires-Dist: pytest-cov==7.0.0 ; extra == "tests"
Project-URL: documentation, https://heart.health.docs.pyansys.com/
Project-URL: issues, https://github.com/ansys/pyansys-heart/issues
Project-URL: releases, https://github.com/ansys/pyansys-heart/releases
Project-URL: source, https://github.com/ansys/pyansys-heart
Provides-Extra: doc
Provides-Extra: tests
